chromedriver_downloader/__init__.py
chromedriver_downloader/chromedriver_downloader.py
chromedriver_downloader-0.1.0.dist-info/AUTHORS.rst
chromedriver_downloader-0.1.0.dist-info/LICENSE
chromedriver_downloader-0.1.0.dist-info/METADATA
chromedriver_downloader-0.1.0.dist-info/WHEEL
chromedriver_downloader-0.1.0.dist-info/top_level.txt
chromedriver_downloader-0.1.0.dist-info/RECORD
